LICENSE
MANIFEST.in
README.md
meta.json
setup.py
en_chem_ner/__init__.py
en_chem_ner/meta.json
en_chem_ner.egg-info/PKG-INFO
en_chem_ner.egg-info/SOURCES.txt
en_chem_ner.egg-info/dependency_links.txt
en_chem_ner.egg-info/entry_points.txt
en_chem_ner.egg-info/not-zip-safe
en_chem_ner.egg-info/requires.txt
en_chem_ner.egg-info/top_level.txt
en_chem_ner/en_chem_ner-0.1.0/LICENSE
en_chem_ner/en_chem_ner-0.1.0/README.md
en_chem_ner/en_chem_ner-0.1.0/config.cfg
en_chem_ner/en_chem_ner-0.1.0/meta.json
en_chem_ner/en_chem_ner-0.1.0/tokenizer
en_chem_ner/en_chem_ner-0.1.0/ner/cfg
en_chem_ner/en_chem_ner-0.1.0/ner/model
en_chem_ner/en_chem_ner-0.1.0/ner/moves
en_chem_ner/en_chem_ner-0.1.0/tok2vec/cfg
en_chem_ner/en_chem_ner-0.1.0/tok2vec/model
en_chem_ner/en_chem_ner-0.1.0/vocab/key2row
en_chem_ner/en_chem_ner-0.1.0/vocab/lookups.bin
en_chem_ner/en_chem_ner-0.1.0/vocab/strings.json
en_chem_ner/en_chem_ner-0.1.0/vocab/vectors
en_chem_ner/en_chem_ner-0.1.0/vocab/vectors.cfg