Metadata-Version: 2.4
Name: en_chem_ner
Version: 0.1.0
Summary: A named entity recognition model for chemical entities.
Home-page: 
Author: Dinga Wonanke
Author-email: dak52@uclive.ac.nz
License: MIT
License-File: LICENSE
Requires-Dist: spacy<3.8.0,>=3.7.5
Dynamic: author
Dynamic: author-email
Dynamic: description
Dynamic: license
Dynamic: license-file
Dynamic: requires-dist
Dynamic: summary
